{
  "version": "5",
  "dialect": "mysql",
  "id": "6b1468da-f36b-442e-8545-0e7fc8623c61",
  "prevId": "b7308b1b-693a-4454-aff1-3c191b4dad81",
  "tables": {
    "users": {
      "name": "users",
      "columns": {
        "id": {
          "name": "id",
          "type": "serial",
          "primaryKey": true,
          "notNull": true,
          "autoincrement": true
        },
        "username": {
          "name": "username",
          "type": "text",
          "primaryKey": false,
          "notNull": true,
          "autoincrement": false
        },
        "password": {
          "name": "password",
          "type": "varchar(256)",
          "primaryKey": false,
          "notNull": true,
          "autoincrement": false
        }
      },
      "indexes": {},
      "foreignKeys": {},
      "compositePrimaryKeys": {}
    }
  },
  "schemas": {},
  "_meta": {
    "schemas": {},
    "tables": {},
    "columns": {}
  }
}